ecosia_images/__init__.py
ecosia_images/ecosia_search.py
ecosia_images-0.6.4.dist-info/LICENSE
ecosia_images-0.6.4.dist-info/METADATA
ecosia_images-0.6.4.dist-info/WHEEL
ecosia_images-0.6.4.dist-info/top_level.txt
ecosia_images-0.6.4.dist-info/RECORD
