Metadata-Version: 2.1
Name: ecosia-images
Version: 0.6.4
Summary: Python module for searching and downloading images from Ecosia
Home-page: https://github.com/Heladio-ac/python-ecosia-images
Author: Heladio Amaya
Author-email: heladio.ac@gmail.com
License: UNKNOWN
Platform: UNKNOWN
Requires-Dist: selenium
Requires-Dist: requests
